pylibsimba/__init__.py
pylibsimba/base/__init__.py
pylibsimba/base/simba_base.py
pylibsimba/base/transaction_base.py
pylibsimba/base/wallet_base.py
pylibsimba/exceptions.py
pylibsimba/pages.py
pylibsimba/simba.py
pylibsimba/transaction_response.py
pylibsimba/util.py
pylibsimba/wallet.py
pylibsimba-0.3.0.dist-info/LICENSE
pylibsimba-0.3.0.dist-info/WHEEL
pylibsimba-0.3.0.dist-info/METADATA
pylibsimba-0.3.0.dist-info/RECORD
