Metadata-Version: 2.1
Name: pylibsimba
Version: 0.3.0
Summary: A library simplifying the use of SIMBAChain APIs
Author: ian.harvey
Author-email: ian.harvey@simbachain.com
Requires-Python: >=3.8,<4.0
Classifier: Programming Language :: Python :: 3
Classifier: Programming Language :: Python :: 3.8
Classifier: Programming Language :: Python :: 3.9
Requires-Dist: hdwallet (>=1.1.1,<2.0.0)
Requires-Dist: web3 (>=5.18.0,<6.0.0)
